mode_manager_mcp/__init__.py
mode_manager_mcp/__main__.py
mode_manager_mcp/instruction_manager.py
mode_manager_mcp/memory_optimizer.py
mode_manager_mcp/path_utils.py
mode_manager_mcp/server_registry.py
mode_manager_mcp/simple_file_ops.py
mode_manager_mcp/simple_server.py
mode_manager_mcp/simple_server_new.py
mode_manager_mcp/types.py
mode_manager_mcp/tools/__init__.py
mode_manager_mcp/tools/instruction_tools.py
mode_manager_mcp/tools/memory_tools.py
mode_manager_mcp/tools/remember_tools.py
iflow_mcp_niclasolofsson_mode_manager_mcp-2.0.2.dist-info/METADATA
iflow_mcp_niclasolofsson_mode_manager_mcp-2.0.2.dist-info/WHEEL
iflow_mcp_niclasolofsson_mode_manager_mcp-2.0.2.dist-info/entry_points.txt
iflow_mcp_niclasolofsson_mode_manager_mcp-2.0.2.dist-info/licenses/LICENSE
iflow_mcp_niclasolofsson_mode_manager_mcp-2.0.2.dist-info/RECORD
