Metadata-Version: 2.4
Name: iflow-mcp_niclasolofsson_mode-manager-mcp
Version: 2.0.2
Summary: Mode Manager MCP: Server for managing VS Code .instructions.md files (GitHub Copilot persistent memory)
Project-URL: Homepage, https://github.com/NiclasOlofsson/mode-manager-mcp
Project-URL: Repository, https://github.com/NiclasOlofsson/mode-manager-mcp
Project-URL: Issues, https://github.com/NiclasOlofsson/mode-manager-mcp/issues
Project-URL: Documentation, https://github.com/NiclasOlofsson/mode-manager-mcp#readme
Author-email: Niclas Olofsson <nicke.olofsson@gmail.com>
License: MIT
License-File: LICENSE
Keywords: github-copilot,instruction,mcp,memory,mode-manager,prompts,vscode
Classifier: Development Status :: 5 - Production/Stable
Classifier: Intended Audience :: Developers
Classifier: License :: OSI Approved :: MIT License
Classifier: Programming Language :: Python :: 3
Classifier: Programming Language :: Python :: 3.10
Classifier: Programming Language :: Python :: 3.11
Classifier: Programming Language :: Python :: 3.12
Requires-Python: >=3.10
Requires-Dist: fastmcp>=2.11.0
Requires-Dist: mcp>=1.12.0
Requires-Dist: psutil>=7.0.0
Requires-Dist: pydantic>=2.0.0
Requires-Dist: tiktoken>=0.5.0
Requires-Dist: typing-extensions
Provides-Extra: dev
Requires-Dist: pre-commit>=3.0.0; extra == 'dev'
Requires-Dist: pydocstringformatter>=0.4.0; extra == 'dev'
Requires-Dist: pyright>=1.1.0; extra == 'dev'
Requires-Dist: pytest-asyncio>=0.21.0; extra == 'dev'
Requires-Dist: pytest>=7.0.0; extra == 'dev'
Requires-Dist: types-psutil; extra == 'dev'
Requires-Dist: types-requests; extra == 'dev'
